{
    "menu": [
    {
        "url": "/dashboard",
        "name": "Dashboard",
        "icon": "menu-icon tf-icons bx bx-home-circle",
        "slug": "pages-home"
    },
    {
        "url": "/intezetek",
        "name": "Intézetek",
        "icon": "menu-icon tf-icons bx bx-buildings",
        "slug": "pages-institutes"
    },
    {
        "url": "/",
        "name": "Folyamatok",
        "icon": "menu-icon tf-icons bx bx-directions",
        "slug": "workflows",
        "submenu": [
            {
                "url": "/folyamatok/nyitott",
                "name": "Nyitott folyamatok",
                "slug": "workflows-all-open"
            },
            {
                "url": "/folyamatok/lezart",
                "name": "Lezárt folyamatok",
                "slug": "workflows-all-closed"
            },
            {
                "url": "/",
                "name": "Felvételi kérelem",
                "slug": "workflows-employee-recruitment",
                "submenu":[
                    {
                        "url": "/felveteli-kerelem/uj",
                        "name": "Új felvételi kérelem",
                        "slug": "workflows-employee-recruitment-new"
                    },
                    {
                        "url": "/felveteli-kerelem/nyitott",
                        "name": "Nyitott felvételi kérelmek",
                        "slug": "workflows-employee-recruitment-open"
                    },
                    {
                        "url": "/felveteli-kerelem/lezart",
                        "name": "Lezárt felvételi kérelmek",
                        "slug": "workflows-employee-recruitment-closed"
                    }
                ]
            }
        ]
    },
    {
        "url": "/felhasznalok",
        "name": "Felhasználók",
        "icon": "menu-icon tf-icons bx bx-user",
        "slug": "pages-user-list"
    },
    {
        "url": "/",
        "name": "Szerepek & Jogok",
        "icon": "menu-icon tf-icons bx bx-check-shield",
        "slug": "authorizations",
        "submenu": [
            {
                "url": "/szerepkorok",
                "name": "Szerepkörök",
                "slug": "authorizations-roles"
            },
            {
                "url": "/jogosultsagok",
                "name": "Jogosultságok",
                "slug": "authorizations-permissions"
            }
        ]
    },
    {
        "url": "/auth/register-basic",
        "name": "Beállítások",
        "icon": "menu-icon tf-icons bx bx-cog",
        "slug": "auth-register-basic",
        "target": "_blank"
    },
    {
        "url": "/",
        "name": "Segédadatok",
        "icon": "menu-icon tf-icons bx bx-data",
        "slug": "auxiliary-data",
        "submenu": [
            {
                "url": "/segedadat/intezetek",
                "name": "Intézet",
                "slug": "auxiliary-data-institute"
            },
            {
                "url": "/segedadat/csoportok",
                "name": "Csoport",
                "slug": "auxiliary-data-workgroup"
            }
        ]
    }
    ]
}
